[
    {
        "title": "bitwise подавать заявка запуск etf основа токен xrp",
        "text": "курс криптовалюта ripple labs отреагировать заявление подавать secкомпания bitwise подавать заявление регистрация биржевой фонд etf основа криптовалюта xrp ripple labs комиссия ценный бумага биржа сша secbitwise позиционировать крупный быстрорастущий управляющий криптоактив компания предлагать широкий ряд инвестиционный инструмент 2024 год компания запускать аналогичный биржевой фонд биткоин ethereumвзаявкеговорится функция администратор фонд выполнять bank of new york mellon coinbase custody хранитель средство фонд bitwise xrp etfrbcgroupтак называть спотовой etf exchange traded fund подразумевать фактический покупка криптовалюта обеспечение акция фонд запуск сша etf спровоцировать приток капитал рынок становиться катализатор рост цена биткоин 2024 годуцель фонд bitwise заключаться стремление обеспечивать доступ xrp находиться распоряжение фонд вычет операционный расход обязательство говориться заявление кроме компания написать документ xrp являться ценный бумага опровергать ранний утверждение secво имя индустрия почему ripple labs открыто противостоять secсудебное разбирательство ripple sec продолжаться декабрь 2020 год сторона спорить являться xrp ценный бумага 2023 год суд постанавливать токен ripple labs являться продажа розничный инвестор sec предпринимать попытка оспаривать решение суд отклонять ходатайство комиссия разбирательство продолжаетсятелеграмканал рбккрипто подписываться курс самый главный актуальный новость криптовалютеприсоединяться кфорум рбккрипт telegram обсуждение новость тенденция криптомирать начало год глава ripple labs брэд гарлингхаусзаявлять положительно смотреть создание биржевой фонд основа токен xrp отказываться раскрывать конкретный план вопросекурс xrp практически отреагировать подача заявление bitwise криптовалюта ripple упасть цена прошедший сутки 4 рамка общий падение курс топ10 актив крипторынок 26 1800 мск 2 октябрь xrp торговаться отметка 058в ноябрь 2023 год появление ложный заявка составлять компания blackrock готовиться создание биржевой фонд xrpвызваловременный скачок цена криптовалюта токен вырастать 12 течение получас появление первый сообщение становиться известно сообщение ложный цена xrp откатиться предыдущий значениямск заводить дело против криптосервис uaps cryptex оборот 112 млрдтокен wormhole вырастать 20 время спад крипторынок это монетапуть наверх простой говорить индикатор крипторынкакурс биткоин упасть новость план иран ударять израилюрбккриптозапускать мониторинг криптовалютный обменник выбирать надежный обменный сервис выгодный курс наyourcryptoexruили удобномтелеграмбота"
    },
    {
        "title": "ск заводить дело против криптосервис uaps cryptex оборот 112 млрд",
        "text": "неделя ранее голова организатор cryptex власть сша объявлять награда 10 млнв москва возбуждать уголовный дело отношение создатель анонимный платежный система uaps криптовалютный биржа cryptexсообщилаофициальный представитель ск россия светлана петренко ранее 2 октябрясталоизвестный связывать дело масштабный операция ход который сотрудник мвд проводить десяток обыск санктпетербург ленобластипо данные следствие 2013 год фигурант дело разрабатывать инфраструктура вид анонимный платежный система uaps криптовалютный биржа cryptex 33 онлайнсервис помощь сервис вестись нелегальный деятельность прием выдача денежный средство обмен валюта криптовалютыпояснилаофициальный представитель мвд ирина волкследствие выяснять организатор выпускать свой банковский карта предоставлять доступ операция личный онлайнкабинет клиент сеть слово волк часто человек который заниматься противоправный деятельность мочь совершать закрывать сервис анонимный перевод обналичивать криминальный доходыrbcgroupпо данные ск 2023 год оборот поступать денежный средство сервис преступный сообщество составлять 112 млрд руб преступный доход фигурант составлять 37 млрд рубв рамка расследование уголовный дело место жительство осуществление преступный деятельность организатор участник преступный сообщество 14 субъект российский федерация проводить 148 обыск москва доставляться 96 фигурант проводиться необходимый следственный действиятелеграмканал рбккрипто подписываться курс самый главный актуальный новость криптовалютеприсоединяться кфорум рбккрипт telegram обсуждение новость тенденция криптомираследстенный комитет возбуждать уголовный дело организатор криптосервис обвинять создание преступный сообщество участие немой неправомерный доступ компьютерный информация неправомерный оборот средство платеж незаконный банковский деятельностиз неделя это конец сентябрь минфин сшаналожилсанкция cryptex россиянин сергей иванов который являться администратор сервис версия американский регулятор госдепартамент сша предлагать вознаграждение размер 10 млн который приводить арест ииль обвинительный приговор отношение ивановасервис cryptex данные ведомство зарегистрировать сентвинсент гренадины название international payment service provider минфин сша утверждать cryptex проходить транзакция сумма 720 млн связывать сервис часто использовать российский разработчик программвымогатель киберпреступникамипо данные власть сша иванов 20 год заниматься отмывание деньги свой клиент проводить транзакция сотня миллион доллар число платежный система uapsкриптостартапы собирать 26 млрд третий квартал топ10 инвестраундовтокен wormhole вырастать 20 время спад крипторынок это монетапуть наверх простой говорить индикатор крипторынкакурс биткоин опускаться 60 тыс происходить крипторынок"
    },
    {
        "title": "токен wormhole вырастать 20 время спад крипторынок это монета",
        "text": "южнокорейский участник крипторынок ожидать начало торги токен крупный местный биржекриптовалюта wormhole w подорожать сутки 215 время большинство цифровой монетупал цена последний неделя цена токен w вырастать 486 неделя 889wormhole кроссчейнпротокол который позволять переводить средство разный блокчейн пользователь блокировать актив блокчейн получать копия это крупный крипторынок проект сумма привлечение венчурный капиталавый начало апрель 2024 год wormhole проводить эирдроп токен раздача листинг криптобиржа курс w вырастать максимум 133 минимум показывать начало август отметка 017 1520 мск 1 октябрь актив торговаться 037 капитализация составлять 965 млнrbcgroupрост wormhole проходить фон сообщение листинг токен криптобиржа upbit платформаобъявлять торги токен w начинаться вечер 2 октябрь пар биткоин btc корейский вона krw стейблкоин usdtкрупнейшая южный корея криптобиржа upbit несколько обходить coinbase okx объем торги порядок 80 объем корейский площадка составлять альткоин который пользоваться местный трейдер гораздо больший популярность биткоин ethereumв первый квартал 2024 год южнокорейский вона krwобогналадоллар сша объем торги криптобиржа уступать показатель торговый пара usdtв конец май анонс листинг токен stg auction beam upbitпривелк резкий рост цена криптовалюта подорожать 80телеграмканал рбккрипто подписываться курс самый главный актуальный новость криптовалютеприсоединяться кфорум рбккрипт telegram обсуждение новость тенденция криптомирать ноябрь 2023 год проект wormhole привлекать 225 млн оценка 25 млрд инвестор становиться фонд coinbase ventures multicoin capital jump trading arrington capital несколько криптокомпания оценка высоко 1 млрд смочь привлекать инвестиция 2023 год раунд инвестиция wormhole становиться самый крупный нихва третий квартал 2024 год меньший мера 340 криптостартаповсобралиболее 265 млрд ход инвестиционный раунд средство 100 млн период смочь привлекать проект celestia модульный блокчейн предоставлять возможность создавать блокчейн основеть санктпетербург полиция начинать проводить обыск криптообменникахпуть наверх простой говорить индикатор крипторынкакурс биткоин упасть новость план иран ударять израилюактивность розничный криптотрейдер низкий должно изменитьсярбккриптозапускать мониторинг криптовалютный обменник выбирать надежный обменный сервис выгодный курс наyourcryptoexruили удобномтелеграмбота"
    },
    {
        "title": "санктпетербург полиция начинать проводить обыск криптообменник",
        "text": "мероприятие рамка который проводить задержание затрагивать общий сложность 14 регион число фигурант дело превышать 90 человекв санктпетербург сотрудник управление экономический безопасность региональный гу мвд проводить обыск десяток адрес связывать незаконный криптообменник сообщать местный издание поданным47news действие возглавлять приезжать москва сотрудник мвд россииисточник близкий мвд подтверждать рбк проведение петербург обыск связывать функционирование криптообменниковподаннымисточник 78ru уголовный дело возбуждать статья ук рф ст 210 организация преступный сообщество ст 172 незаконный банковский деятельность ст 187 неправомерный оборот средство платежейrbcgroupтелеграмканал рбккрипто подписываться курс самый главный актуальный новость криптовалютеприсоединяться кфорум рбккрипт telegram обсуждение новость тенденция криптомирамероприятие рамка который проводить задержание затрагивать общий сложность 14 регион число фигурант дело превышать 90 человек писать журналист данные 78ru дело вести отдел расследование особо важный дело столичный управление следственный комитетав 47news сообщать ход текущий операция особый внимание силовик направлять дом поселок лисий нос приморский район петербург версия мвд проживать организатор криптовалютный схема обналичивание средстврбк направлять запрос прессцентр мвд рф ск рфв конец сентябрь становиться известно москвепресеклиработа обменник криптовалюта оборот 200 млн руб нелегальный обменный пункт помогать клиент выводить средство граница скрываться вывеска туристический компанийпо данные следствие злоумышленник московский обменник заниматься незаконный банковский деятельность оказывать услуга обналичивание перевод средство граница криптовалюта получать доход особо крупный размере26 сентябрь минфин сшаналожилсанкция криптообменник pm2btc cryptex администратор версия американский регулятор администратор оба сервис являться гражданин россия имя сергей иванов власть сша обвинять сервис связь отмывание незаконный доходовранее сентябрь власть германиизаявлять конфисковать сервер полусотня криптообменник больший часть сервис русскоязычный онлайнобменникамипуть наверх простой говорить индикатор крипторынкакурс биткоин опускаться 60 тыс происходить крипторынкеактивность розничный криптотрейдер низкий должно изменитьсядоход майнер биткоин продолжать падать сентябрь это считать"
    },
    {
        "title": "путь наверх простой говорить индикатор крипторынок",
        "text": "показатель отражать накопление биткоин долгосрочный инвестор ожидание рост считать аналитикибиткоин btc закрывать сентябрь рекордный последний 11 год рост настроение крипторынок отражать жадность участник ожидание позитивный цифровой актив октябряоднако 1 октябрь курсы криптовалюта обвалиться фон эскалация конфликт ближний восток рынок отреагировать усиление геополитический напряженность традиционно нефть золото начинать дорожать рисковой актив дешеветь индекс страх жадность крипторынок вернуться зона страх спустя неделя покинулволна ликвидация падение курс вызывать самый большой убыток трейдер начало август сутки биржа принудительно закрывать позиция ставить рост криптовалюта общий сумма 453 млнrbcgroupрыночные условие последний несколько неделя включая глобальный денежнокредитный политика обещание поддержка криптосектор кандидат президент сша указывать бычий тренд расчет аналитик эксперт прогнозировать btc достигать 70 тыс октябретелеграмканал рбккрипто подписываться курс самый главный актуальный новость криптовалютеприсоединяться кфорум рбккрипт telegram обсуждение новость тенденция криптомиранесмотря нестабильность курс вызывать ираноизраильский конфликт настроение повод осеннезимний динамика курс биткоин оставаться позитивный говорить старший аналитик cryptorg андрей подолянсогласно технический анализ цена btc март год находиться огромный расширяться клин рассказывать эксперт слово ожидаться подход курс верхний грань клинаклин фигура технический анализ сторона представлять поддерживать линия тренд второй сторона линия сопротивление выход курс клин идти сторона противоположный направление движение фигурыграфик цена биткоин источник binanceпрямо цена монета дневной таймфрейм находиться медвежий облако зона сопротивление большой вероятность игрок начинать продавать объяснять подолян зона проходиться быстро поэтому путь наверх прямой простой говорить аналитикчто касаться план октябрь хотеться хотя подходить глобальный трендовый линия район 69 тыс успешный пробой ожидать движение ширина клин район 90 тыс заявлять экспертпредположение технический анализ биткоин подтверждать биржевой метрика добавлять подолян данные аналитический сервис биткоин покупать выводить биржа причем биржа выводиться btc туда поступать это позитивный знак утверждать аналитиккоэффициент обменный поток 30d 365d индикатор который показывать соотношение краткосрочный 30дневными долгосрочный 365дневными приток отток btc биржа говорить рынок готовиться следующий восходящий трендуотметилить cryptoquantbtc exchange flow multiple источник cryotpquantкогда обменный поток многократно снижаться это означать краткосрочный приток отток биржа значительно мало долгосрочный показатель упасть минимум год это мочь отражать накопление средство инвестор пояснять аналитикиони отмечать ситуация похожий сценарий ранний стадия бычий рынок опытный участник предпочитать выходить свой позиция ожидать дальнейший рост ценный 1300 мск 1 октябрь биткоин торговаться около 611 тыс суточный снижение цена 44активность розничный криптотрейдер низкий должно изменитьсядоход майнер биткоин продолжать падать сентябрь это считалибанк россия исследовать криптоплатеж россиянин это возможноминута цена 3 млн проходить запуск токен криптопроект eigenlayerрбккриптозапустил мониторинг криптовалютный обменник выбирать надежный обменный сервис выгодный курс наyourcryptoexruили удобномтелеграмбота"
    },
    {
        "title": "курс биткоин опускаться 60 тыс происходить крипторынок",
        "text": "ведущая криптовалюта начало исторически удачный октябрь падениякурс биткоин btc начинать традиционно удачный актив октябрь падение ночь 2 октябрь цена первый криптовалюта опускаться 603 тыс фонеэскалацииконфликт ближний востокеbtcusd60 70013 002окхoct 02 2333181д3д1м3м1г5леще сутки назад btc торговаться около 64 тыс утро 2 октябрь курс монета колебаться около 617 тыс 24 час подешеветь 36rbcgroupобщая капитализация крипторынок сутки упасть 49 227 трлн объем торги цифровой актив время превышать 150 млрд данные coingeckoиндекс страх жадность крипторынок снова опускаться зона страх 42 балл 100 низко отметка находиться 17 сентябрятелеграмканал рбккрипто подписываться курс самый главный актуальный новость криптовалютеприсоединяться кфорум рбккрипт telegram обсуждение новость тенденция криптомиракурс ethereum eth 24 час опускаться 242 тыс альткоин подешеветь 63 сутки 1030 мск цена монета составлять около 248 тысethusd2 3826718 293окхoct 02 2332511д3д1м3м1г5лкурсы криптовалюта топ10 капитализация прошедший 24 час также показывать снижение подешеветь сильный dogecoin doge 82 маленький падение монета tron trx проседать 14 курс toncoin ton упасть 54из топ100 криптовалюта капитализация прошедший сутки самый сильный рост wormhole w подорожать 149 самый большой снижение монета arweave ar подешеветь 153по данные сервис coinglass отслеживать сделка крупный криптобиржа прошедший 24 час совокупный объем принудительно закрытый длинный позиция достигать 453 млн ликвидировать ордер 526 млнс ликвидация сталкиваться около 155 тыс трейдер который хватить средство поддержание открытый позиция рынок пойти против ставка большинство потеря зафиксировать ставить рост btc ethсамый крупный ордер ликвидация происходить биржа binance пара btcusdt сумма 1266 млноктябрь криптосообщество называть uptober англ up вверх считать самый удачный месяц биткоин последний 11 год 5 бычий ралли btcстартовалив октябрь аналитик прогнозировать актив мочь обновлять месяц свой максимумактивность розничный криптотрейдер низкий должно изменитьсядоход майнер биткоин продолжать падать сентябрь это считалибанк россия исследовать криптоплатеж россиянин это возможноминута цена 3 млн проходить запуск токен криптопроект eigenlayerрбккриптозапустил мониторинг криптовалютный обменник выбирать надежный обменный сервис выгодный курс наyourcryptoexruили удобномтелеграмбота"
    },
    {
        "title": "курс биткоин упасть новость план иран ударять израиль",
        "text": "цена первый криптовалюта обвалиться 15 тыскурс биткоин btc упасть фон новость план иран запускать баллистический ракета израиль цена актив обвалиться 15 тыс сталоизвестноо возможный подготовка удараbtcusd60 70013 002окхoct 02 2333181д3д1м3м1г5лперед сообщение биткоин торговаться 635 тыс течение полтора час новость курс btc опускаться 619 тыс 1820 мск цена первый криптовалюта колебаться около 621 тысrbcgroupтелеграмканал рбккрипто подписываться курс самый главный актуальный новость криптовалютеприсоединяться кфорум рбккрипт telegram обсуждение новость тенденция криптомираобщать капитализация крипторынок время упасть 130 млрд 2327 трлн подавлять число котировка криптовалюта топ100 опускаться красный зона цифровой актив подешеветь вслед ведущий криптовалюта данные coingeckoкотировки нефть золото наоборот резковырасти цена декабрьский фьючерс оба актив пойти вверханалитика крипторынок ранее давать оптимистический прогноз отношение текущий динамика биткоин говорить множество фактор способствовать рост менее экспертыпредупреждать негативный фактор оставаться высокий вероятность эскалация конфликт ближний востокедоход майнер биткоин продолжать падать сентябрь это считалибанк россия исследовать криптоплатеж россиянин это возможноминута цена 3 млн проходить запуск токен криптопроект eigenlayerисторически бычий месяц биткоин повторять октябрьский раллирбккриптозапускать мониторинг криптовалютный обменник выбирать надежный обменный сервис выгодный курс наyourcryptoexruили удобномтелеграмбота"
    },
    {
        "title": "доход майнер биткоин продолжать падать сентябрь это считать",
        "text": "хешрейт сеть вырастать несмотря снижение сложность добыча первый криптовалютыдоходы майнер биткоин показывать снижение третий месяц подряд подсчитывать аналитик jpmorganсообщаетcoindesk суточный доходность прибыль добыча криптовалюта упасть фон продолжаться рост хешрейт сеть биткоинапо оценка jpmorgan сентябрь майнер получать вознаграждение среднее 421 тыс час оборудование мощность 1 экзахэш секунда ehs 6 мало месяц ранее валовой прибыль период также упасть 6 161 тыс ehs написать аналитикив общий сложность сентябрь майнер зарабатывать 80224 млн 3 маленький 82756 млн август 13 маленький 92735 млн июль поданнымbitborbcgroupв время ключевой показатель рентабельность майнинг биткоин bitcoin hashprice index 30 сентябрь находиться уровень 46 высоко значение конец август составлять около 42bitcoin hashprice index июльсентябрь источник hashrate indexиндекс вводить американский майнинговый компания luxor technologies значение показывать сколько мочь зарабатывать день майнер вычислительный мощность 1 петахеш секунда phsна пик конец 2021 год показатель достигать 35 тыс начало 2024 год халвинг 20 апрель находиться диапазон 77 120 халвинг индикатор подскакивать 139 счет высокий комиссия который получать майнер средний размер комиссия вернуться норма значение hashprice основной снижалосьрентабельность майнинг август превышать сентябрьский счет скачок индекс 53 середина последний летний месяц состояние 1 октябрь bitcoin hashprice index находиться уровень 4582телеграмканал рбккрипто подписываться курс самый главный актуальный новость криптовалютеприсоединяться кфорум рбккрипт telegram обсуждение новость тенденция криптомиратем время хешрейт сеть биткоин вырастать сентябрь третий месяц подряд август увеличиваться 2 643 ehs это сложность майнинг конец сентябрь упасть 46 884 тобычно сложность майнинг расти вместе рост хешрейт это позволять сохранять график эмиссия криптовалюта изменение ожидаться следующий перерасчет происходить 10 октябрь онпонизитпоказатель 296крупные майнер рассчитывать рост цена биткоин который мочь существенно повлиять доходность добыча cleansparkожидают курс btc приближаться 200 тыс горизонт полтора год второй капитализация майнер сша придерживаться стратегия hodl копить добывать биткоин рассчитывать продавать цена высокий текущейбанк россия исследовать криптоплатеж россиянин это возможноминута цена 3 млн проходить запуск токен криптопроект eigenlayerисторически бычий месяц биткоин повторять октябрьский ралливый казахстан начало год закрывать 19 криптообменник оборот 60 млнрбккриптозапускать мониторинг криптовалютный обменник выбирать надежный обменный сервис выгодный курс наyourcryptoexruили удобномтелеграмбота"
    },
    {
        "title": "банк россия исследовать криптоплатеж россиянин это возможный",
        "text": "19 кредитный организация обязанный предоставлять регулятор данные связанный цифровой актив операция клиентовфизлицбанк россииопубликовалпрограмма обследование финансовый рынок близкий полгода согласно документ iv квартал 2024 год i квартал 2025 год выбирать банк должный сообщать регулятор трансграничный перевод россиянин связывать приобретение криптоактивовобследование проводиться цель установление возможность идентификация совокупный объем трансграничный денежный перевод физический лицо операция связывать покупкойпродажа криптоактив оценка стоимостный объем говориться документ цбв обследование участвовать мтсбанк райффайзенбанк ситибанк банк союз юникредит банк 13 банк кредитный организация сбер втб тбанк список опубликовывать приложение программа цб значатсяrbcgroupцель сбор информация контроль движение капитал предотвращение незаконный операция разработка мера регулирование криптовалютный рынок говорить советник практика интеллектуальный собственность юридический компания эбр эксперт mds кристина мкртчян слово также цб использовать данные корректировка денежнокредитный политика понимать объем денежный средство уходить рубеж поступать странупрограмма обследование банк россия впервыеанонсированыть 2017 год рассказывать преподаватель образовательный платформа moscow digital school дмитрий кириллов цель программа регулятор указывать унификация оптимизация процесс сбор обработка информация участник финрынок разработка единый подход управление даннымить часть криптовалютный перевод цб планировать запрашивать 19 крупный банк следующий информация операция способ перевод наименование платежный система сторона перевод код страна банк говорить кириллов уточнять также банк россия интересовать код валюта перевод количество сумма перевод число квалифицировать банкомреспондент подозрительный операциителеграмканал рбккрипто подписываться курс самый главный актуальный новость криптовалютеприсоединяться кфорум рбккрипт telegram обсуждение новость тенденция криптомирабанка выявлять трансграничный перевод физический лицо связывать покупка криптовалюта помощь код данные контрагент особенно средство отправляться криптобиржа объяснять мкртчян слово описание платеж указывать покупка криптовалюта перевод биржа банк мочь классифицировать операция связывать криптовалютойва время эксперт усомниться точность результат обследование собирать цб информация мнение кириллов довольно приблизительный поскольку далеко весь операция совершаться криптобиржа купляпродажа криптовалюта p2p мочь однозначно идентифицировать говорить экспертp2pпереводы отслеживать сложно перевод биржа соглашаться предыдущий специалист мкртчян однако операция мочь связывать зарубежный счет который гражданин обязанный сообщать это позволять банк сопоставлять списание p2p зачисление добавлять юристкриптовалюта широко использоваться россиянин несмотря недавний полный отсутствие регулирование сфера 2024 год страназаняласедьмой место глобальный рейтинг принятие криптовалюта август россиюпришлосьдо 28 трафик крупный криптобиржахкриптовалютный оборот россия первый половина 2024 годадостиг23 трлн руб согласно анализ транзакция популярный страна криптообменник биржа проводить компания шард кроме аналитика отмечать уход крупный мир криптобиржа binance россия часть пользователь перемещаться биржа рублевый p2pплатформбанк россия женазываетраспространение цифровой денежный суррогат мир криптовалюта стейблкоин фактор который мочь угрожать стабильность отечественный рынок регулятор категорически исключать использование криптовалюта внутри россия рамка эксперимент готовиться запускать проведение трансграничный криптоплатеж конец 2024 годаминута цена 3 млн проходить запуск токен криптопроект eigenlayerисторически бычий месяц биткоин повторять октябрьский ралливый казахстан начало год закрывать 19 криптообменник оборот 60 млнтокен hamster kombat упасть 40 запуск монета tonрбккриптозапустил мониторинг криптовалютный обменник выбирать надежный обменный сервис выгодный курс наyourcryptoexruили удобномтелеграмбота"
    },
    {
        "title": "исторически бычий месяц биткоин повторять октябрьский ралли",
        "text": "первый криптовалюта 5 начинать свой рост новый максимум середина осениза последний 11 год 5 бычий ралли биткоин стартовать октябрь 2013 2017 2020 2021 2023 год первый криптовалюта начинать рост свой новый исторический максимум начало iv кварталаотметилианалитика платформа lookonchainоктябрь год ралли график биткоин источник lookonchainпрогнозы участник рынок биткоин второй месяц осень оптимистичный исторически октябрь это бычий месяц 8 последний 9 октябрь средний рост btc составлять 229 поданнымqcp capital аналитик подсчитывать подобный рост год мочь позволять биткоин превышать отметка 78 тыс побивать исторический максимумыrbcgroupтелеграмканал рбккрипто подписываться курс самый главный актуальный новость криптовалютеприсоединяться кфорум рбккрипт telegram обсуждение новость тенденция криптомирарынок рассматривать возможность большой прорыв btc считать qcp capital это мочь способствовать надвигаться выборы президент сша стабильно положительный приток средство спотовой etf также рост финансирование бессрочный фьючерс напоминать ситуация бычий рынок i квартал год полагать экспертыстрах аппетит риск готовиться биткоин октябрекурс первый критовалюта достигать исторический максимум отметка 737 тыс 14 март год 1 январь цена биткоин колебаться около 422 тыс первый 25 месяц год вырастать 75btcusd60 70013 002окхoct 02 2333181д3д1м3м1г5лпрошедший сентябрь биткоинзакрылс рекордный 11 год рост традиционно слабый месяц криптовалюта btc подорожать 729 1400 мск 1 октябрь ведущий цифровой актив торговаться 639 тысв казахстан начало год закрывать 19 криптообменник оборот 60 млнтокен hamster kombat упасть 40 запуск монета tonрегулирование крипторынок 2024 год страна использовать криптовалютыанлоки токен конференция важный криптовалюта событие октябрярбккриптозапускать мониторинг криптовалютный обменник выбирать надежный обменный сервис выгодный курс наyourcryptoexruили удобномтелеграмбота"
    },
    {
        "title": "казахстан начало год закрывать 19 криптообменник оборот 60 млн",
        "text": "глава финразведка снг договариваться сотрудничество противодействие новый угроза включая нелегальный майнинг использование криптовалюта преступникамить казахстан начало год ликвидировать 19 криптообменник оборот 60 млнсообщилипредставитель агентство финансовый мониторинг афм 28м заседание совет руководитель подразделение финансовый разведка српфрпомимо ликвидация нелегальный 19 криптообменник оборот 60 млн начало год казахстан закрывать 55 тыс незаконный онлайнобменник также зарегистрировать девять дело отношение серый майнер изымать 4 тыс устройство майнинг замораживать криптовалюта 12 млнсрпфр это отраслевой орган снг создавать 2012 год входить семь страна россия казахстан армения белоруссия кыргызстан узбекистан таджикистан заседание српфр проходить поле международный олимпиада финансовый безопасность сочи участник обсуждать вопрос взаимодействие финансовый разведка странучастницrbcgroupв афм заявлять сфера противодействие незаконный оборот криптовалюта работа проводиться направление нелегальный майнинг незаконный криптообменник противоправный операция цифровой активамителеграмканал рбккрипто подписываться курс самый главный актуальный новость криптовалютеприсоединяться кфорум рбккрипт telegram обсуждение новость тенденция криптомирать афм сообщать создавать спецподразделение криптовалюта внедрять практика изъятие ход следствиячее промышленный майнер отличаться бытовой разница россия сшапо итог заседание српфр глава финразведка страна участница совет договариваться объединять усилие совершенствование метод противодействие новый угроза сообщать афмс конец 2022 год казахстан майнигсталлицензировать деятельность добывать криптовалюта власть разрешать аккредитовать казахстанский пул потреблять электроэнергия напрямую общий энергосеть майнер исключительно наличие избыткать нелегальный майнер продолжать свой деятельность территория казахстан конец сентябрь астанезакрыликрупный незаконный майнингферма работать вид сервис обслуживание двигатель изымать это около 13 тыс устройство майнингать время казахстан поддерживать развитие криптовалютный индустрия рамка закон территория международный финансовый центр астана мфца разрешать деятельность криптовалютный биржа платформа связывать цифровой активами30 сентябрь глава binance ричард тенгсообщать подразделение биржа казахстан получать полный лицензия ведение бизнес страна ранее месяц согласие оформление полный лицензия управление финансовый услуга астана afsa получать криптобиржа bybitкурс биткоин закрывать сентябрь рекордный 11 год ростомтокен hamster kombat упасть 40 запуск монета tonрегулирование крипторынок 2024 год страна использовать криптовалютыанлоки токен конференция важный криптовалюта событие октябрярбккриптозапускать мониторинг криптовалютный обменник выбирать надежный обменный сервис выгодный курс наyourcryptoexruили удобномтелеграмбота"
    },
    {
        "title": "курс биткоин закрывать сентябрь рекордный 11 год рост",
        "text": "прошедший сентябрь становиться самый доходный первый криптовалюта 11 леткурс биткоин btc закрывать сентябрь рекордный рост цена первый криптовалюта вырастать последний 30 день 729 предыдущий 11 год максимальный рост btc сентябрь составлять 604 2016 год поданнымglassnodebtcusd60 70013 002окхoct 02 2333181д3д1м3м1г5лв течение первый месяц осень цена биткоин опускаться 534 тыс подниматься 663 тыс 1100 мск 1 октябрь ведущий криптовалюта торговаться около 64 тыс сутки подешеветь 09rbcgroupethereum eth сентябрь подорожать 7 264 тыс последний сутки 03ethusd2 3826718 293окхoct 02 2332511д3д1м3м1г5лобщая капитализация крипторынок сентябрь вырастать 2163 трлн 241 трлн 11 индекс страх жадность начало осень находиться зона страх уровень 26 балл 100 30 сентябрь показатель подниматься сектор жадность 61 балл 1 октябрь индекс показывать нейтральный настроение 50 балловтелеграмканал рбккрипто подписываться курс самый главный актуальный новость криптовалютеприсоединяться кфорум рбккрипт telegram обсуждение новость тенденция криптомиракурс криптовалюта топ10 капитализация сентябрь основной показывать рост самый сильный подорожание dogecoin doge solana sol порядок 20 курс toncoin ton подниматься 83экспертысклоняютсяк позитивный развитие событие крипторынок октябрь прогноз курс биткоин мочь штурмовать отметка 70 тыс первый криптовалюта очень важно проходить зона 65 тыс закрепляться это определять дальнейший движение курс криптовалюта полагать аналитикитокен hamster kombat упасть 40 запуск монета tonрегулирование крипторынок 2024 год страна использовать криптовалютыанлоки токен конференция важный криптовалюта событие октябрярухнуть биржа ftx выплачивать клиент миллиард сколько получитрбккриптозапускать мониторинг криптовалютный обменник выбирать надежный обменный сервис выгодный курс наyourcryptoexruили удобномтелеграмбота"
    },
    {
        "title": "анлоки токен конференция важный криптовалюта событие октябрь",
        "text": "второй месяц осень насыщенный важный сфера криптовалюта крупный криптопроект событие рассказывать обращать внимание9 октябряstacks stx хардфорк nakamotoхардфорк nakamoto крупный обновление сеть stacks который активировать 9 октябрь направлять улучшение производительность сеть счет ускорение производство блок повышение надежность транзакция избегать проблема оператор узел майнер нужно обновлять программный обеспечение времениrbcgroupхардфорк интегрироваться блокчейн биткоин усиливать связь сеть вводить новый возможность смартконтракт децентрализованный приложенийстейкинг выгодный defiпроекты сеть биткоина1316 октябряконференци future blockchain summit 2024 дубаеfuture blockchain summit 2024 состояться 13 16 октябрь дубай это крупный мероприятие область блокчейн криптовалюта который объединять 150 спикер 150 экспозиция 1200 инвестор саммит являться часть масштабный проект gitex global включать конференция финтеху стартап fintech surge expand north starсреди известный спикер глава cardano foundation фредерик грегаард председатель blockchain research institute дон тапскотт соучредитель the sandboxсебастьен боржа соучредитель hacken дмитрий будорина другий ход мероприятие проходить мастеркласс нетворкинг конкурс стартапов supernova challenge1517 октябрь 2024debridge dbr запуск платформа jupiter launchpadзапуск продажа токен debridge dbr платформа jupiter launchpad запланировать 15 октябрь 2024 год токен доступный покупка фиксированный цена 0025 выпускать 200 млн токен составлять 2 общий объем 10 миллиард dbr это означать общий сумма инвестиция этап запуск превышать 5 млн запуск токен token generation event tge запланировать 17 октябрятоп3 торговый платформа solana главный dex токен сетипродажа токен представлять улучшать версия предыдущий запуск токен который часто заканчиваться убыток инвестор debridge использовать механизм launch fair and grow lfg который предусматривать участник отбирать 28 тыс разрешать адрес смочь приобретать токен одинаковый цена это 50 токен доступный сразу запуск остальной 50 распределять течение шесть месяцевтакже планироваться выделение 10 общий объем токен инициатива сообщество 5 пойти нужда debridge foundation 3 развитие экосистема оставаться 82 распределять равномерно течение лет1618 октябряконференция web3 summit 2024 берлинеweb3 summit 2024 важный событие посвящать развитие децентрализованный интернет который пройти 16 18 октябрь берлинеконференция собирать ведущий разработчик исследователь энтузиаст весь мир обсуждение ключевой аспект децентрализация безопасность взаимодействие экосистема web3 среди спикер выделять соучредитель ethereum polkadot гэвин вуд ведущий научный сотрудник microsoft research жарон ланьер глава protocol labs хуан бенетг соучредитель chainlink сергей назаровпрограмма мероприятие включать мастеркласс сессия вопрос ответ лидер отрасль лекция особый внимание уделять инновация сотрудничество рамка мероприятие пройти хакатон участник смочь работать свой проект обмениваться идея сотрудничатьтелеграмканал рбккрипто подписываться курс самый главный актуальный новость криптовалютеприсоединяться кфорум рбккрипт telegram обсуждение новость тенденция криптомираоктябрь 2024разблокировки токеновва октябрь 2024 год ожидаться значительный объем разблокировка токен различный криптопроект мочь повлиять рыноккогда проект выходить рынок циркулировать находиться рынок предложение токен ограничивать команда инвестор разный уровень сотрудник тд иметь токен рука создавать дополнительный давление цена монета правило токен участник заблокировать определенный срок несколько месяц несколько летэти участник начинать получать монета мочь продавать рынок согласно график определять токеномика экономический модель проект процесс называться разблокировка токеновcelestia tia крупный анлок намечать 30 октябрь 17556 млн токен эквивалентный 112 млрдsui sui 6419 млн токен сумма около 108 млн разблокировать 1 октябряaptos apt 113 млн токен сумма около 91 млн разблокировать 11 октябряsolana sol токен сумма 360 млн выпускать течение октябряarbitrum arb ожидаться разблокировка 9265 млн токен эквивалентный примерно 6190 млнcardano ada разблокировка около 1853 млн токен 2 октябрь сумма около 75 млнкром токен проект immutable imx optimism op zetachain zeta galxe gal mode mode neon neon starknet strk также разблокировать суммарно добавлять значительный ликвидность рынок общий стоимость разблокировать токен месяц мочь превышать 346 млрдкрупный майнер поставлять биткоин 200 тыс это случитсястра аппетит риск готовиться биткоин октябререзультат доходность намеривать заниматься эксглава binanceтоп20 перспективный криптовалюта 2024 год главное отчет grayscaleрбккриптозапустил мониторинг криптовалютный обменник выбирать надежный обменный сервис выгодный курс наyourcryptoexruили удобномтелеграмбота"
    },
    {
        "title": "токен hamster kombat упасть 40 запуск монета ton",
        "text": "криптовалюта четыре популярный тапалка telegram торговаться высоко свой стартовый ценыкурс криптовалюта hamster kombat hmstr обвалиться 40 несколько день проходить листинг криптобиржа недавно запущенный также блокчейн ton токен dogs dogs catizen cati также упасть цена последний неделюпри старт торги 26 сентябрь цена hmstrсоставила001 1630 мск 30 сентябрь токен торговаться 00057 данные coinmarketcap момент запуск цена упасть 43hamster kombat последний ряд криптовалюта выпускать настоящий момент популярный миниприложение telegram категория taptoearn проект предлагать пользователь зарабатывать управлять виртуальный криптобиржа качество персонажахомякаrbcgrouphamster kombat привлекать 300 млн пользователь данные разработчик популярность игра отчасти обязанный успех предыдущий тапалка мессенджер notcoin not dogs dogs catizen catihamster kombat blum ждать токен тапалка telegramпервым выходить биржа токен notcoin пользователь приложение мессенджер добывать токен просто нажимать экран смартфон листинг токен not криптобиржа проводить 16 май год следующий день листинг павел дуровотметилуспех notcoin сообщать день выход биржа not входить топ10 криптовалюта торговый объем капитализация достигать 700 млнnotcoin единственный топ5 криптовалюта экосистема ton показывать существенный рост последний неделя цена not вырастать семь день 20 момент запуск актив подешеветь старт цена равняться 00016 30 сентябрь not давать 00008телеграмканал рбккрипто подписываться курс самый главный актуальный новость криптовалютеприсоединяться кфорум рбккрипт telegram обсуждение новость тенденция криптомиратокен dogs выходить биржа 26 август суть игра сводиться начисление участник токен зависимость дата регистрация аккаунт telegram приглашение новый пользователь реферальный системеажиотаж вокруг криптовалюта настолько большой сеть tonпроизошелмасштабный сбой изза высокий нагрузка сеть производить блок транзакция течение семь часовпо сравнение токен hmstr dogs подешеветь сильно начало торги конец август 00008329 курс упасть примерно 4 0000820 сентябрь биржа начинаться торги catizen проект отличаться тапалка предлагать полноценный игровой механика пользователь размножать котенок повышать уровень цена cati стартовать 06263 мало неделя вечер 30 сентябрь опускаться 23 05884несмотря снижение цена токен недавно нашуметь кликер курс нативный криптовалюта самый блокчейн toncoin ton вырастать неделя 3непременная детелеграмизация ton telegramмонета прочно закрепляться топ10 криптовалюта капитализация общий рыночный стоимость ton составлять 30 сентябрь 147 млрд время близкий последователь рейтинг tron trx cardano ada попеременно занимать десятый 11е место капитализация около 135 млрдпо мнение аналитик тапалка становиться экосистема ton инструмент привлечение ликвидность новый активный пользователь несмотря позитивный прогноз экспертыопасаться успех ton мочь нивелировать окончание эпоха популярность приложенийкликеровкрупный майнер поставлять биткоин 200 тыс это случитсястра аппетит риск готовиться биткоин октябререзультат доходность намеривать заниматься эксглава binanceтоп20 перспективный криптовалюта 2024 год главное отчет grayscaleрбккриптозапустил мониторинг криптовалютный обменник выбирать надежный обменный сервис выгодный курс наyourcryptoexruили удобномтелеграмбота"
    },
    {
        "title": "крупный майнер поставлять биткоин 200 тыс это случаться",
        "text": "глава cleanspark ожидать цена криптовалюта совершать значительный скачок близкий месяц длительный время вернуться медвежий циклугенеральный директор американский майнинговый компания cleanspark зак брэдфорд ожидать биткоин цикл достигать пик 200 тыспишетthe blockcleanspark clsk второй капитализация компания среди американский майнер оценка конец май 2024 годапревышала443 млрд компания владеть примерно 8 тыс btc 509 млн датацентр cleanspark общий мощность 1 гвт располагать штат джорджия миссисипи ньюйорк теннесси вайомингосновываться текущий анализ полагать мочь увидеть пик биткоин низко 200 тыс гдето близкий 18 месяц вероятно это пик действительно думать увидеть быстрый скачок затем надеяться длительный период возврат медвежий цикл сказать брэдфорд интервью аналитик брокерский фирма bernsteinrbcgroupодной причина свой прогноз называть длительный период консолидация биткоин показывать устойчивый рост мочь продолжаться долго менее зависеть макроэкономический событие фактор добавлять брэдфордпо слово глава cleanspark значительный рост цена биткоин начинаться январь должный приводить значительный увеличение маржа майнер хороший позиция эффективный структура затрата момент исчезать неопределенность связанный сегодня выборы президент сша фрс проводить агрессивный снижение ставка становиться хороший предзнаменование биткоин уверенный бизнесментелеграмканал рбккрипто подписываться курс самый главный актуальный новость криптовалютеприсоединяться кфорум рбккрипт telegram обсуждение новость тенденция криптомираcleanspark фокусироваться исключительно добыча биткоин хотя брэдфорд признавать частичный переключение датацентр нужда ия связывать это эффективный модель затрата сыграть рука крупный конкурент cleansparkснижение доход майнер фон халвинг побуждать компания искать новый способ монетизация технический решение база свой мощность американский майнер core scientific заключать 12летнее соглашение провайдер облачный услуга coreweave сумма 35 млрд нужда обучение модель ия hive digital начинать использовать свой дримощность облачный технология который лежать основа чатбот chatgpt hut 8 привлекать 150 млн развитие проект поддержка иидатацентр майнинг адаптировать нужда ия почему это выгоднопо слово брэдфорд главное майнер правильно определять момент рынок стратегия cleanspark заключаться продажа добывать биткоин пики рынок накопление спад компания удерживать 97 добывать биткоин июнь 2023 год намерен продавать накоплять будущий бычий период финансирование ростав связь быстрый развитие оборудование майнинг брэдфорд также ожидать чип новый поколение достигать эффективность 11 jth майнер приходиться переходить воздушный охлаждение оборудование иммерсионный жидкостный cleanspark это заниматься сказать брэдфорд иммерсионный охлаждение оборудование майнинг издавать шум воздушный система вентиляцииоднако производительность майнинговый ферма достигать 15 jth выгода переход новый чип ограничивать мочь приводить снижение стоимость оборудование майнинг считать брэдфорд настоящий момент компания bitmain ужезапустилапредпродажа asicмайнеров bitcoin miner s21 pro заявлять энергоэффективность 15 jthкурс биткоин упасть 2 тыс обновление локальный максимуматоп20 перспективный криптовалюта 2024 год главное отчет grayscaleигра это криптовалюта китайский автомобильва криптовалютный сеть переходить капитал сентябрь топ4 проектоврбккриптозапускать мониторинг криптовалютный обменник выбирать надежный обменный сервис выгодный курс наyourcryptoexruили удобномтелеграмбота"
    },
    {
        "title": "страх аппетит риск готовиться биткоин октябрь",
        "text": "эксперт называть фактор который мочь повлиять цена криптовалюта последний квартал год давать прогноз курс btc близкий месяцрбккрипто давать инвестиционный совет материал опубликовывать исключительно ознакомительный цель криптовалюта это волатильный актив который мочь приводить финансовый убыткамкурс биткоин btc начало сентябрь вырастать 8 59 тыс 64 тыс несмотря первый криптовалюта удаваться закрепляться высоко локальный минимум 66 тыс btc пытаться закрывать первый месяц осень плюсеbtcusd60 67142 007окхoct 02 2333001д3д1м3м1г5лrbcgroupэксперты рассказывать рбккрипто ожидание крипторынок октябрь давать прогноз цель случай позитивный негативный сценариеврезультат ожиданийбиткоин проводить отличный сентябрь завершать месяц относительно хороший рост говорить управляющий партнер vg group вагиз нурулл отмечать это рекордный показатель btc 2013 год исторически первый криптовалюта именно сентябрь торговаться минусизменение цена биткоин месяц источник coinglassсохранение биткоин позиция август хороший итог первый осенний месяц считать эксперт однако результат мнение оказываться ожидание сентябрь актив торговаться диапазон 525 тыс 655 тыс 27 сентябрь btc обновлять максимум 31 июль отметка около 663 тысный позитиведальный поведение ведущий криптовалюта зависеть ряд условие рассказывать ведущий аналитик bitget research райан слово рост биткоин мочь поддерживать оптимистичный настроенияэксперт перечислять фактор который подкреплять мнение потенциал позитивный движение биткоинаожидание победа выборы президент сша ноябрь год дональд трамп который считаться прокриптовалютный кандидатомприток актив биткоинetfсмягчение политика комиссия ценный бумага биржа сша sec качество пример аналитик приводить вычеркивание криптовалюта solana sol список незаконно выпускать ценный бумага отсутствие препятствие путь запуск спотовой ethereumetf также слабость глава sec гэри генслер выступление конгрессомперенесенный выплата кредитор ftx часть который мочь оседать криптоактивахнарастание дефицит btc рынок халвинг апрель 2024 годаоптимизм добавлять возможный вливание ликвидность рынок сторона власть китай который образ хотеть поддерживать банковский сектор полагать литакже многие ждать переход фрс увеличение выпуск доллар фон завершение борьба американский регулятор инфляция переход власть новый рука говорить эксперт пояснять новый администрация президент мочь использовать печатный станок залатать дыра экономика прогноз решение постепенно закладывать рынок октябрь смочь увидеть эффекткак решение фрс макродать сша влиять криптовалюта учитыватькром обращать внимание большинство участник рынок ждать дальнейший движение фрс путь снижение ключевой ставка изменение постепенно повышать инвестиционный привлекательность высокорискованный актив криптовалютыинвестор следить динамика рост потребительский цена пытаться предугадывать происходить снижение ключевой ставка следующий заседание фрс который намечать начало ноябрь говорить сооснователь encry foundation роман некрасов эксперт пояснять инфляция продолжать снижаться это утверждать участник рынок мнение ноябрь ставка снова понижать повышать аппетит рисковый активампопытка штурмабиткоин входить октябрь торговаться район 64 тыс суметь преодолевать давление медведь пытаться удерживать низко 60 тыс говорить некрасов эксперт полагать первый криптовалюта октябрь протестировать 70 тыс случай позитивный сценарий отсутствие страх стагфляциейсовокупность фактор иметь шанс подталкивать биткоин вверх подтверждать райан аналитик прогнозировать аналогичный цель актив октябрь биткоин мочь предпринимать попытка штурм 70 тыстелеграмканал рбккрипто подписываться курс самый главный актуальный новость криптовалютеприсоединяться кфорум рбккрипт telegram обсуждение новость тенденция криптомираважно отмечать статистически октябрь являться феноменальный месяц биткоин позитив крипторынок выливаться текущий событие выборы период понижение ставка выплата ftx напоминать нурулл ожидать октябрь год биткоин торговаться диапазон 58 тыс 70 тыс монета возможно улетать новый высотывозможный проблемывпереди отчет основа который фрс принимать дальнейший решение ставка рассказывать исключать оптимистичный ожидание инвестор оправдаютсяразочарование действие фрс мочь остужать крипторынок сдвигать позитивный эффект близко конец год считать аналитик слово случай исключать спуск btc 50 тысне настолько негативный прогноз поделиться роман некрасов мнение инвестор охватывать страх сохраняться высокий инфляция смягчение ключевой ставка рисковой актив число биткоин криптовалюта мочь испытывать волна распродажа который вернуть btc обратно 60 тыспопрежний оставаться риск рецессия сша также высокий вероятность эскалация конфликт ближний восток добавлять нурулл аналитик отмечать также смущать излишне большой позитив криптосообщество название участник месяц октябрь uptober англ up вверх эксперт указывать ожидание масса часто совпадать действительностьюважный уровнипока картина оптимистичный сценарий выигрывать считать аналитик bitget слишком долго btc копить сила новый рывок поэтому эксперт склоняться позитивный сценарий штурм 70 тыс октябрепо мнение некрасов октябрь пока выглядеть достаточно оптимистичный отчасти рост аппетит риск инвестор заметный индекс страх жадность считать аналитик показатель подниматься зона жадность выше 60 балл держаться четыре днябиткоин очень важно проходить зона 65 тыс закрепляться говорить нурулл слово аналитик это определять дальнейший движение криптовалютыкурс биткоин упасть 2 тыс обновление локальный максимуматоп20 перспективный криптовалюта 2024 год главное отчет grayscaleигра это криптовалюта китайский автомобильва криптовалютный сеть переходить капитал сентябрь топ4 проектоврбккриптозапускать мониторинг криптовалютный обменник выбирать надежный обменный сервис выгодный курс наyourcryptoexruили удобномтелеграмбота"
    },
    {
        "title": "результат доходность намеривать заниматься эксглава binance",
        "text": "эксглава крупный криптобиржа чанпэн чжао раскрывать свой план близкий времяоснователь binance чанпэн чжао выходить свобода отбывать решетка четыре месяц миллиардерпообещалпродолжать инвестировать индустрия блокчейн активно участвовать жизнь криптосообщество опубликовывать первое освобождение изпод стража сша сообщение сеть хва апрель чжао приговаривать тюремный заключение нарушение закон банковский тайна норма борьба отмывание средство binance руководство проходить 15 млн транзакция сумма около 900 млн связывать финансирование терроризм незаконный операция форма нарушение американский санкция миллиардер признавать вина выплачивать штраф 50 млн отбывать назначать срок лишение свободыпродолжать инвестировать блокчейн децентрализовать технология ия биотехнология долгосрочный инвестор который волновать результат проект доходность написать чжаоrbcgroupбизнесмен признаваться продолжать работать книга слово треть готовый чжао также планировать посвящать время средство благотворительность забывать это участвовать жизнь криптосообщество посещать конференцииего новый начинание некоммерческий образовательный онлайнплатформа giggle academy становиться большой часть жизнь цель giggle academy предоставлять глобальный доступ бесплатный образование ребенок малообеспеченный семейтелеграмканал рбккрипто подписываться курс самый главный актуальный новость криптовалютеприсоединяться кфорум рбккрипт telegram обсуждение новость тенденция криптомираbinance крупный мир криптовалютный биржа соответствие сделка признание вина чжао уходить пост главный исполнительный директор передавать бразды правление ричард тенгув начало сентябрь binance пожизненноотстранилачжао управление хотя минюст сша требовать запрещать участие управление биржа ограничивать должность предполагаться год чжао оставаться мажоритарный акционер binance хотя формально числиться совет директоровбизнесмен отмечать свой сообщение binance похоже прекрасно справляться мечта каждый основатель написать чжаопосле отставка биржа руководство тенг открыто заявлять взять курс сотрудничество регулятор раскрывать данные совет директор решать открывать официальный штабквартирубиржа придерживаться глобальный санкционный регулирование полностью соблюдать ограничение отношение физический юридический лицо страна попадать международный санкция заявлять представитель это официально уходить россия платформапродолжаетрабатывать некоторый россиянамикурс биткоин упасть 2 тыс обновление локальный максимуматоп20 перспективный криптовалюта 2024 год главное отчет grayscaleигра это криптовалюта китайский автомобильва криптовалютный сеть переходить капитал сентябрь топ4 проектоврбккриптозапускать мониторинг криптовалютный обменник выбирать надежный обменный сервис выгодный курс наyourcryptoexruили удобномтелеграмбота"
    },
    {
        "title": "курс биткоин упасть 2 тыс обновление локальный максимум",
        "text": "цена первый криптовалюта добираться рекордный сентябрь отметка удерживаться вернуться значение предыдущий неделикурс биткоин btc упасть 2 тыс обновление локальный максимум выходной 2829 сентябрь цена btc достигать 663 тыс впервые 31 июль продержаться диапазон 653663 тыс течение день утро понедельник 30 сентябрь курс первый криптовалюта опускаться 2 тыс 64 тысbtcusd60 70013 002окхoct 02 2333181д3д1м3м1г5лна 1030 мск биткоин торговаться около 644 тыс сутки подешеветь 17 неделя подорожать 12 доля рынок btc составлять 5732 данные tradingviewrbcgroupethereum eth последний 24 час упасть цена 05 264 тыс недельный отрезок цена ведущий альткоин также показывать снижение 06ethusd2 3826718 293окхoct 02 2332511д3д1м3м1г5лобщая капитализация крипторынок составлять 238 трлн сутки опускаться 18 индекс страх жадность попрежнему оставаться зона жадность опускаться 63 балл 61 100телеграмканал рбккрипто подписываться курс самый главный актуальный новость криптовалютеприсоединяться кфорум рбккрипт telegram обсуждение новость тенденция криптомиракурс несколько криптовалюта топ10 капитализация прошедший 24 час показывать небольшой рост остальной снижение самый сильный подорожание xrp xrp ripple вырастать цена 27 подешеветь сильно dogecoin doge 28 курс toncoin ton вырастать 08из топ100 криптовалюта капитализация прошедший сутки самый сильный рост bittensor tao подорожать 102 самый большой снижение монета shiba inu shib подешеветь 4на текущий неделя внимание инвестор сосредотачивать выступление глава фрс джером пауэлл 30 сентябрь также публикация ряд важный экономический показатель включая данные рынок труд сша индекс деловой активность ismпредупреждаютаналитики целое ожидать позитивный динамика крипторынок предупреждать конец неделя рынок смочь активно отрастать риск коррекция возрастуттоп20 перспективный криптовалюта 2024 год главное отчет grayscaleигра это криптовалюта китайский автомобильва криптовалютный сеть переходить капитал сентябрь топ4 проектакак связанный дуров хомяк топ запрос яндекс hamster kombatрбккриптозапустил мониторинг криптовалютный обменник выбирать надежный обменный сервис выгодный курс наyourcryptoexruили удобномтелеграмбота"
    },
    {
        "title": "игра это криптовалюта китайский автомобиль",
        "text": "проверять смочь отличать название токен новый китайский автобрендовэто криптовалюта китайский автомобильпроверять смочь отличать название токен новый китайский автобрендовначать тест1 10давайте взять чтото простой разминка нужно угадывать это криптовалюта бренд китайский автомобиляsolanaкриптовалютаправильно solana пятый капитализация криптовалюта самый популярный рынок монеткитайский автомобильневерно разработчик криптовалюта solana выпускать смартфон игровой консоль производство автомобиль пока дошло2 10мы проходить простой разминочный вопрос далеко сразу погружаться недра китайский автопром криптотокен глубина рейтинг продолжимtaikoкриптовалютавы правый taiko tko это криптотокен капитализация 150 млн торговаться биржа второй эшелон весь входить топ300 крупный монеткитайский автомобильназвание казаться действительно созвучно какимто автобренд увы это криптовалюта3 10продолжим стараться пользоваться поисковик знание интуиция итак следующий вариант это авто криптотокенeverusкриптовалютаошибка несколько токен название который присутствовать слово ever это нихкитайский автомобильверный 2008 год предприятие guangqi honda решать создавать бренд everus совместно китаец everus ve1 например являться электромобиль база honda vezel4 10сразу думаяzinoroкриптовалютаа монета рынок это автомобилькитайский автомобильправильный zinoro это китайский bmw например zinoro 1e являться электромобиль база bmw e84 впервые показывать автосалон гуанчжоу 2013 году5 10продолжаем задачка сложно это криптотокен автомобильumaкриптовалютаверно токен uma торговаться крупный биржа включая binance это платформа выпуск криптоактив поддержка несколько именитый венчурный компанийкитайский автомобильнеправильно существовать трехбуквенный бренд автомобиль это них6 10у очередной кандидат считать это монета продукт китайский автопромаzentryкриптовалютаверно снова криптовалюта самый популярный монета binance вполне торговаться bybit okx мелкий площадкахкитайский автомобильзвучать както похоже соглашаться увы это криптомонета7 10что сказать насчет следущий вариант звучать токен бренд авто правда лиcotiкриптовалютаверно это действительно токен капитализация 200 млн binance крупный биржахкитайский автомобильнуть снова криптовалюта8 10итак вариант это повашемуkaweiкриптовалютаа вполне китайский автомобиль крипта неткитайский автомобильправильно бренд kawei auto принадлежать находиться город danyang провинция jiangsu компания kawei automotive industry group выпускать пикап самосвал автобус микроавтобусы9 10в прошлый вопрос попадаться автомобиль разlympoкриптовалютаверно малоизвестный токен lym листинг биржа bitfinex kucoin токен зарабатывать синхронизировать платформа lympo приложение трекинг здоровье крайний мера это заявлять разработчикикитайский автомобильневерно криптовалютный токен10 10заключительный вопрос это криптовалюта автомобильvenuciaкриптовалютавот автомобиль китайский производствакитайский автомобильверный марка venucia запускать сентябрь 2010 год компания dongfeng nissan цель продажа автомобиль разрабатывать китай специально внутренний рынкадальше0из 10попробуйте сновадействительно легко запутываться брать самый неочевидный вариант оба сфер0из 10неплоховы гдеть путаться целый отличать крипторынок автомобильного0из 10отличнопохоже очень ориентироваться криптовалютный автомобильный рынок поздравляемпройти разiiтелеграмканал рбккрипто подписываться курс самый главный актуальный новость криптовалютеприсоединяться кфорум рбккрипт telegram обсуждение новость тенденция криптомир"
    },
    {
        "title": "связанный дуров хомяк топ запрос яндекс hamster kombat",
        "text": "вообще играть хомяк вывести зарабатывать токен хотеть знать пользователь популярный миниприложение telegram26 сентябрь криптобиржизапустилиторги токен hamster kombat hmstr игровой миниприложение telegram информация команда hamster kombat количество пользователь проект превышать 300 млн игра хомяк главный роль становиться самый популярный среди тапалка годуяндекс добавлять токен hmstr свой конвертер криптовалютзапущенныйв февраль 2023 год запрос строка поиск сервис определять искать пользователь это распознавать сленг например почем догикоин эфир евро курс хомяк рубль виджет график курс поддерживать 144 криптовалютыаналитика яндекс проводить исследование запрос яндекс поиск касаться игра hamster kombat подборка иметься распоряжение рбккрипто показывать именно хотеть знать пользователь поисковик hamster kombat март сентябрь 2024 годаrbcgroupв hamster kombat несколько игровой механик самый известный который нажимать хомяк экран запрос пользователь описывать действие разный глагол наиболее популярный тапать тыкать кликать встречаться необычный вариант например давить хомяк хомяк который жмакатьура плюс 4 хороший комментарий hamster kombat форум рбккриптосреди весь запрос hamster kombat подавлять большинство посвящать механик игра 90 половина случай пользователь интересоваться комбинация игровой карточка например карточка сегодня хомяк треть запрос связанный ежедневный шифр последовательность символ азбука морзе примерно 4 случай пользователь просить помогать прохождение миниигр пример перемещать свеча хомяк пошагово запрос посвящать сразу несколько механик например шифр комбо хомяк сегодняеще около 4 запрос связанный листинг токен hmstr криптобиржа также вывод внутриигровый средство пользователь интересоваться листинг хомяк оплачивать хомяк магазин hamster kombat обналичивать деньгив поиск также спрашивать вообще играть hamster kombat например почему тапать хомяк смысл игра хомяк комбат пользователь задавать вопрос реферальный ссылка друг приглашать друг hamster kombat быстро игра хомяк делать друг далеепользователь интересоваться взламывать игра изза это мочь последствие пример среди подобный запрос скачать взламывать версия кликание хомяк получать 1 млн хомяк чит видео бан автокликер hamster kombat hamster kombat почему банить покупка рефераловтелеграмканал рбккрипто подписываться курс самый главный актуальный новость криптовалютеприсоединяться кфорум рбккрипт telegram обсуждение новость тенденция криптомиравстречаться необычный запрос игра например связанный дуров хомяк делать мама хотеть тапать хомяк продолжать пословица хомяк кликать известно хомяк почему знать стоиттоп5 глагол который описывать механика hamster kombatтапатьтапать хомяк зачемчто делать мама хотеть тапать хомякаприспособление тапать хомякатыкатьхомяк деньги тыкатьпочий тыкать хомякакто сколько натыкать монета хомякекликатькогда кликать хомяк доход идетсмертельный случай кликание хомякапродолжать пословица хомяк кликать тотнажиматьчто хомяк который нажимаютнажимать хомяк деньги даеткуда нажимать хомяк загораться краснымнабиватькак набивать хомяк пальцамикак набивать азбука морзе хомякечто важно хомяк прибыль час набилсудя сагрегировать обезличенный запрос интерес игра начинать расти конец май пик достигать июнь первый летний месяц каждый пятисотый запрос сервис посвящать игрежизнь тапалка ton выход hamster kombatbloombergоценил 230 млн состояние глава российский майнер bitriverреестр майнер россия вести фнс почему решилирбккриптозапускать мониторинг криптовалютный обменник выбирать надежный обменный сервис выгодный курс наyourcryptoexruили удобномтелеграмбота"
    }
]